djali/__init__.py
djali/base.py
djali/couchdb.py
djali/dynamodb.py
djali/tools.py
djali-0.5.2.dist-info/METADATA
djali-0.5.2.dist-info/WHEEL
djali-0.5.2.dist-info/licenses/COPYING
djali-0.5.2.dist-info/RECORD
