Metadata-Version: 2.4
Name: djali
Version: 0.5.2
Summary: Key/Value Database Clients
Author-email: doubleO8 <wb008@hdm-stuttgart.de>
License-Expression: GPL-2.0-only
License-File: COPYING
Requires-Python: >=3.6.8
Requires-Dist: boto3>=1.18.21
Requires-Dist: cloudant~=2.12.0
Requires-Dist: six>=1.13.0
